ros_d2/__init__.py
ros_d2/export.py
ros_d2/main.py
ros_d2/helpers/convert.py
ros_d2/helpers/get_ros_architecture.py
ros_d2-1.0.5.dist-info/LICENSE
ros_d2-1.0.5.dist-info/METADATA
ros_d2-1.0.5.dist-info/WHEEL
ros_d2-1.0.5.dist-info/entry_points.txt
ros_d2-1.0.5.dist-info/top_level.txt
ros_d2-1.0.5.dist-info/zip-safe
ros_d2-1.0.5.dist-info/RECORD
