Metadata-Version: 2.1
Name: ros-d2
Version: 1.0.5
Summary: Exports ROS2 nodes into the .d2 diagram format
Home-page: https://github.com/Greenroom-Robotics/ros-d2
Author: Greenroom Robotics
Author-email: team@greenroomrobotics.com
Maintainer: David Revay
Maintainer-email: david.revay@greenroomrobotics.com
License: Copyright (C) 2022, Greenroom Robotics
Keywords: colcon
Classifier: Development Status :: 3 - Alpha
Classifier: Environment :: Plugins
Classifier: Intended Audience :: Developers
Classifier: Programming Language :: Python
Classifier: Topic :: Software Development :: Build Tools
License-File: LICENSE
Requires-Dist: toml (~=0.10)
Requires-Dist: setuptools
Requires-Dist: colorama
Requires-Dist: click
Requires-Dist: py-d2
